bionorm/__init__.py
bionorm/__version__.py
bionorm/attributes.py
bionorm/busco_normalizer.py
bionorm/common.py
bionorm/consistency.py
bionorm/extract_fasta.py
bionorm/generate_readme.py
bionorm/index.py
bionorm/installer.py
bionorm/metadata.py
bionorm/prefix.py
bionorm/specification_checks.py
bionorm/templates/readme/correspondence.yml
bionorm/templates/readme/file_descriptions.yml
bionorm/templates/readme/organism.yml
bionorm/templates/readme/readme.yml
bionorm/templates/readme/strains.yml
bionorm-0.7.11.dist-info/entry_points.txt
bionorm-0.7.11.dist-info/LICENSE
bionorm-0.7.11.dist-info/WHEEL
bionorm-0.7.11.dist-info/METADATA
bionorm-0.7.11.dist-info/RECORD
