Metadata-Version: 2.1
Name: bionorm
Version: 0.7.11
Summary: normalize, verify, and select genomic data
Home-page: https://github.com/legumeinfo/bionorm
License: BSD-3-Clause
Keywords: science,biology,bioinformatics,genomics,data science,DNA,protein,sequences,FASTA,GFF,curation,wrangling
Author: Connor Cameron
Author-email: ctc@ncgr.org
Maintainer: Joel Berendzen
Maintainer-email: joelb@ncgr.org
Requires-Python: >=3.6.1,<4.0.0
Classifier: Development Status :: 5 - Production/Stable
Classifier: Environment :: Console
Classifier: Intended Audience :: Science/Research
Classifier: License :: OSI Approved :: BSD License
Classifier: Natural Language :: English
Classifier: Operating System :: OS Independent
Classifier: Programming Language :: Python :: 3
Classifier: Programming Language :: Python :: 3.6
Classifier: Programming Language :: Python :: 3.7
Classifier: Programming Language :: Python :: 3.8
Classifier: Programming Language :: Python :: 3.9
Classifier: Topic :: Scientific/Engineering :: Bio-Informatics
Requires-Dist: addict (>=2.2.1,<3.0.0)
Requires-Dist: ansimarkup (>=1.4.0,<2.0.0)
Requires-Dist: biopython (>=1.76,<2.0)
Requires-Dist: click (>=7.0,<8.0)
Requires-Dist: click_loguru (>=0.3.6,<0.4.0)
Requires-Dist: click_plugins (>=1.1.1,<2.0.0)
Requires-Dist: importlib_metadata (>=1.5.0,<2.0.0)
Requires-Dist: packaging (>=20.3,<21.0)
Requires-Dist: pandas (>=1.0.3,<2.0.0)
Requires-Dist: progressbar2 (>=3.50.1,<4.0.0)
Requires-Dist: pygit2 (>=1.2.0,<2.0.0)
Requires-Dist: requests_download (>=0.1.2,<0.2.0)
Requires-Dist: ruamel.yaml (>=0.16.6,<0.17.0)
Requires-Dist: sequencetools (>=0.0.5,<0.0.6)
Requires-Dist: sh (>=1.12.14,<2.0.0)
Requires-Dist: toml (>=0.10.0,<0.11.0)
Project-URL: Documentation, https://bionorm.readthedocs.org
